odoo/addons/test_base_import_async/README.rst
odoo/addons/test_base_import_async/__init__.py
odoo/addons/test_base_import_async/__manifest__.py
odoo/addons/test_base_import_async/i18n/test_base_import_async.pot
odoo/addons/test_base_import_async/readme/CONTRIBUTORS.rst
odoo/addons/test_base_import_async/readme/DESCRIPTION.rst
odoo/addons/test_base_import_async/static/description/icon.png
odoo/addons/test_base_import_async/static/description/index.html
odoo/addons/test_base_import_async/tests/__init__.py
odoo/addons/test_base_import_async/tests/account.move.csv
odoo/addons/test_base_import_async/tests/test_base_import_async.py
odoo13_addon_test_base_import_async-13.0.1.0.1.dev5.dist-info/METADATA
odoo13_addon_test_base_import_async-13.0.1.0.1.dev5.dist-info/WHEEL
odoo13_addon_test_base_import_async-13.0.1.0.1.dev5.dist-info/top_level.txt
odoo13_addon_test_base_import_async-13.0.1.0.1.dev5.dist-info/RECORD
