Metadata-Version: 2.1
Name: odoo13-addon-test-base-import-async
Version: 13.0.1.0.1.dev5
Summary: Test suite for base_import_async. Normally you don't need to install this.
Home-page: https://github.com/OCA/queue
Author: ACSONE SA/NV, Odoo Community Association (OCA)
Author-email: support@odoo-community.org
License: AGPL-3
Platform: UNKNOWN
Classifier: Programming Language :: Python
Classifier: Framework :: Odoo
Classifier: Framework :: Odoo :: 13.0
Classifier: License :: OSI Approved :: GNU Affero General Public License v3
Classifier: Development Status :: 5 - Production/Stable
Requires-Python: >=3.5
Requires-Dist: odoo13-addon-base-import-async
Requires-Dist: odoo <13.1dev,>=13.0a
